achive/__init__.py
achive/beanparser/__init__.py
achive/beanparser/callable.py
achive/beanparser/csv_parser.py
achive/beanparser/irt_strategy.py
achive/beanparser/judge.py
achive/beanparser/match.py
achive/cache/__init__.py
achive/cache/orders_map.json
achive/cache/refund_cache_manager.py
achive/downfile/__init__.py
achive/downfile/config.json
achive/downfile/downfile.py
achive/extractfile/__init__.py
achive/extractfile/zip_extract.py
achive/extractfile/zip_password_mutiprocess.py
achive/extractfile/zip_password_simple.py
achive/flow/__init__.py
achive/rules/__init__.py
achive/rules/rules.py
achive/test/__init__.py
achive/test/test.py
achive/utils/__init__.py
achive/utils/utils.py
achive/writefile/__init__.py
achive/writefile/write.py
ir/__init__.py
ir/ir.py
package/__init__.py
package/__main__.py
package/cmd/__init__.py
package/cmd/root.py
package/cmd/trans.py
package/compiler/__init__.py
package/compiler/compiler.py
package/config/__init__.py
package/config/config.py
package/config/init.py
package/enums/__init__.py
package/enums/const.py
package/parser/__init__.py
package/parser/ali/__init__.py
package/parser/ali/alipay.py
package/parser/utils/__init__.py
package/parser/utils/utils.py
package/strategy/__init__.py
package/strategy/template/__init__.py
package/strategy/template/normal.py
package/strategy/template/strategy.py
package/template/__init__.py
package/template/normal.j2
package/template/template.py
provider/__init__.py
provider/provider.py
provider/ali/__init__.py
provider/ali/ali_types.py
provider/ali/alipay.py
provider/ali/converter.py
provider/ali/processor.py
provider/ali/rules.py
bill_flow_enmu-1.0.4.dist-info/METADATA
bill_flow_enmu-1.0.4.dist-info/WHEEL
bill_flow_enmu-1.0.4.dist-info/entry_points.txt
bill_flow_enmu-1.0.4.dist-info/top_level.txt
bill_flow_enmu-1.0.4.dist-info/RECORD
