Metadata-Version: 2.4
Name: bill-flow-enmu
Version: 1.0.4
Summary: bill-generater
License: MIT
Requires-Dist: requests
Requires-Dist: typer
Requires-Dist: pandas
Requires-Dist: openpyxl
Requires-Dist: beautifulsoup4
Requires-Dist: pydantic
Requires-Dist: jinja2
Requires-Dist: pyyaml
